cyst/__init__.py
cyst/api/__init__.py
cyst/api/configuration/__init__.py
cyst/api/configuration/configuration.py
cyst/api/configuration/host/__init__.py
cyst/api/configuration/host/service.py
cyst/api/configuration/infrastructure/__init__.py
cyst/api/configuration/infrastructure/infrastructure.py
cyst/api/configuration/infrastructure/log.py
cyst/api/configuration/infrastructure/physical.py
cyst/api/configuration/logic/__init__.py
cyst/api/configuration/logic/access.py
cyst/api/configuration/logic/data.py
cyst/api/configuration/logic/exploit.py
cyst/api/configuration/network/__init__.py
cyst/api/configuration/network/elements.py
cyst/api/configuration/network/firewall.py
cyst/api/configuration/network/network.py
cyst/api/configuration/network/node.py
cyst/api/configuration/network/router.py
cyst/api/environment/__init__.py
cyst/api/environment/clock.py
cyst/api/environment/configuration.py
cyst/api/environment/control.py
cyst/api/environment/data_model.py
cyst/api/environment/environment.py
cyst/api/environment/external.py
cyst/api/environment/infrastructure.py
cyst/api/environment/interpreter.py
cyst/api/environment/message.py
cyst/api/environment/messaging.py
cyst/api/environment/metadata_provider.py
cyst/api/environment/physical.py
cyst/api/environment/platform.py
cyst/api/environment/platform_interface.py
cyst/api/environment/platform_specification.py
cyst/api/environment/resources.py
cyst/api/environment/stats.py
cyst/api/environment/stores.py
cyst/api/host/__init__.py
cyst/api/host/service.py
cyst/api/logic/__init__.py
cyst/api/logic/access.py
cyst/api/logic/action.py
cyst/api/logic/behavioral_model.py
cyst/api/logic/composite_action.py
cyst/api/logic/data.py
cyst/api/logic/exploit.py
cyst/api/logic/metadata.py
cyst/api/network/__init__.py
cyst/api/network/elements.py
cyst/api/network/firewall.py
cyst/api/network/node.py
cyst/api/network/session.py
cyst/api/utils/__init__.py
cyst/api/utils/counter.py
cyst/api/utils/duration.py
cyst/api/utils/singleton.py
cyst_core-0.6.6.dist-info/entry_points.txt
cyst_core-0.6.6.dist-info/LICENSE.md
cyst_core-0.6.6.dist-info/METADATA
cyst_core-0.6.6.dist-info/WHEEL
cyst_core-0.6.6.dist-info/RECORD
