Metadata-Version: 2.3
Name: cyst-core
Version: 0.6.6
Summary: API and runtime of the CYST framework
Author: Martin Drasar
Author-email: drasar@ics.muni.cz
Requires-Python: ==3.12.*
Classifier: Development Status :: 4 - Beta
Classifier: Intended Audience :: Developers
Classifier: Intended Audience :: Science/Research
Classifier: License :: OSI Approved :: GNU Lesser General Public License v3 (LGPLv3)
Classifier: Operating System :: OS Independent
Classifier: Programming Language :: Python :: 3
Classifier: Programming Language :: Python :: 3.12
Classifier: Topic :: Scientific/Engineering
Classifier: Topic :: Scientific/Engineering :: Artificial Intelligence
Classifier: Topic :: Security
Classifier: Typing :: Typed
Requires-Dist: cachetools (>=5.3.2)
Requires-Dist: deprecated (>=1.2.18,<2.0.0)
Requires-Dist: importlib_metadata (>=6.8.0)
Requires-Dist: jsonpickle (>=3.0.2)
Requires-Dist: netaddr (>=0.9.0)
Requires-Dist: networkx (>=3.2.1)
Requires-Dist: py-flags (>=1.1.4)
Requires-Dist: pyserde (>=0.12.5)
Requires-Dist: semver (>=3.0.2)
Requires-Dist: sqlalchemy (>=2.0.41,<3.0.0)
Project-URL: Homepage, https://muni.cz/go/cyst/
